MANIFEST.in
README
folks.py
setup.py
folks.egg-info/PKG-INFO
folks.egg-info/SOURCES.txt
folks.egg-info/dependency_links.txt
folks.egg-info/entry_points.txt
folks.egg-info/top_level.txt