Metadata-Version: 1.0
Name: folks
Version: 0.1.0
Summary: Manage contacts via CLI
Home-page: https://github.com/chelmertz/folks
Author: Carl Helmertz
Author-email: helmertz@gmail.com
License: UNKNOWN
Platform: UNKNOWN
Classifier: Development Status :: 2 - Pre-Alpha
Classifier: Environment :: Console
